CHANGES.txt
MANIFEST.in
README.rst
TODO.txt
setup.cfg
setup.py
kotti_image_gallery/__init__.py
kotti_image_gallery/resources.py
kotti_image_gallery/views.py
kotti_image_gallery.egg-info/PKG-INFO
kotti_image_gallery.egg-info/SOURCES.txt
kotti_image_gallery.egg-info/dependency_links.txt
kotti_image_gallery.egg-info/not-zip-safe
kotti_image_gallery.egg-info/requires.txt
kotti_image_gallery.egg-info/top_level.txt
kotti_image_gallery/static/css/README.txt
kotti_image_gallery/static/img/README.txt
kotti_image_gallery/static/js/README.txt
kotti_image_gallery/templates/gallery-view.pt
kotti_image_gallery/templates/image-view.pt
kotti_image_gallery/tests/__init__.py
kotti_image_gallery/tests/test_settings.py